noiseframework/__init__.py
noiseframework/cli/__init__.py
noiseframework/cli/main.py
noiseframework/crypto/__init__.py
noiseframework/crypto/cipher.py
noiseframework/crypto/dh.py
noiseframework/crypto/hash.py
noiseframework/noise/__init__.py
noiseframework/noise/handshake.py
noiseframework/noise/pattern.py
noiseframework/noise/state.py
noiseframework/transport/__init__.py
noiseframework/transport/transport.py
noiseframework-1.2.0.dist-info/licenses/LICENSE
noiseframework-1.2.0.dist-info/METADATA
noiseframework-1.2.0.dist-info/WHEEL
noiseframework-1.2.0.dist-info/entry_points.txt
noiseframework-1.2.0.dist-info/top_level.txt
noiseframework-1.2.0.dist-info/RECORD
