Metadata-Version: 2.4
Name: noiseframework
Version: 1.2.0
Summary: A professional, secure, and easy-to-use implementation of the Noise Protocol Framework in Python
Author-email: Julius Pleunes <jjgpleunes@gmail.com>
License-Expression: MIT
Project-URL: Homepage, https://github.com/juliuspleunes4/noiseframework
Project-URL: Documentation, https://github.com/juliuspleunes4/noiseframework/blob/main/README.md
Project-URL: Repository, https://github.com/juliuspleunes4/noiseframework
Project-URL: Issues, https://github.com/juliuspleunes4/noiseframework/issues
Project-URL: Changelog, https://github.com/juliuspleunes4/noiseframework/blob/main/docs/CHANGELOG.md
Keywords: noise,noise-protocol,cryptography,encryption,handshake,security,transport-security,chacha20-poly1305,curve25519
Classifier: Development Status :: 3 - Alpha
Classifier: Intended Audience :: Developers
Classifier: Programming Language :: Python :: 3
Classifier: Programming Language :: Python :: 3.8
Classifier: Programming Language :: Python :: 3.9
Classifier: Programming Language :: Python :: 3.10
Classifier: Programming Language :: Python :: 3.11
Classifier: Programming Language :: Python :: 3.12
Classifier: Topic :: Security :: Cryptography
Classifier: Topic :: Software Development :: Libraries :: Python Modules
Requires-Python: >=3.8
License-File: LICENSE
Requires-Dist: cryptography>=41.0.0
Provides-Extra: dev
Requires-Dist: pytest>=7.0.0; extra == "dev"
Requires-Dist: pytest-cov>=4.0.0; extra == "dev"
Requires-Dist: hypothesis>=6.0.0; extra == "dev"
Requires-Dist: black>=23.0.0; extra == "dev"
Requires-Dist: mypy>=1.0.0; extra == "dev"
Requires-Dist: ruff>=0.1.0; extra == "dev"
Dynamic: license-file
